{
  "item-states": [
    {
      "folded": true,
      "id": "79IGhXcF9KOJ61kN1Qc5oB"
    },
    {
      "folded": true,
      "id": "98R5d6ym9LupuDG36RmDlA"
    },
    {
      "folded": true,
      "id": "55U93GK4NF+britmxhzeY+"
    },
    {
      "folded": false,
      "id": "92Hr4mHOVJJrNRMnHayO/O"
    },
    {
      "folded": true,
      "id": "1d/5LpqDBEL6ejTqT6F/Lk"
    },
    {
      "folded": true,
      "id": "c2lnWExulAZY1I44s03RTC"
    },
    {
      "folded": true,
      "id": "07cHJ1fyZKVooSJmHyBsOX"
    },
    {
      "folded": false,
      "id": "f9dtYZdrlDlIWjb04JtAu2"
    },
    {
      "folded": false,
      "id": "9ba37NlG5HgYPzikd46Ksm"
    },
    {
      "folded": true,
      "id": "d5iLLNaNRLP4KJqPF4yIPR"
    },
    {
      "folded": true,
      "id": "2csQBhOtlO6JtH7I0W/H8B"
    },
    {
      "folded": true,
      "id": "4c8VWT8QlONqIoxfbYjFmm"
    },
    {
      "folded": true,
      "id": "96e+AAhblKi7+bzvYHPm4e"
    },
    {
      "folded": false,
      "id": "d0EY39NbVPi6woyx4JCZAZ"
    }
  ]
}